src/decorators/__init__.py
src/decorators/misc_tools.py
src/decorators/time_tools.py
lb_decorators-0.0.1.dist-info/METADATA
lb_decorators-0.0.1.dist-info/WHEEL
lb_decorators-0.0.1.dist-info/licenses/LICENSE
lb_decorators-0.0.1.dist-info/RECORD
