Metadata-Version: 2.1
Name: lb-decorators
Version: 0.0.1
Summary: Some useful decorators
Project-URL: Homepage, https://github.com/labasef/lb-decorators
Project-URL: Bug Tracker, https://github.com/labasef/lb-decorators/issues
Author-email: labase <github@labase.dev>
License-File: LICENSE
Classifier: License :: OSI Approved :: GNU General Public License v3 (GPLv3)
Classifier: Operating System :: OS Independent
Classifier: Programming Language :: Python :: 3
Requires-Python: >=3.7
